whalegamer_forecast_mcp_online/__init__.py
whalegamer_forecast_mcp_online-0.1.0.dist-info/WHEEL
whalegamer_forecast_mcp_online-0.1.0.dist-info/entry_points.txt
whalegamer_forecast_mcp_online-0.1.0.dist-info/METADATA
whalegamer_forecast_mcp_online-0.1.0.dist-info/RECORD
