Metadata-Version: 2.3
Name: whalegamer-forecast-mcp-online
Version: 0.1.0
Summary: Add your description here
Author: Jker_momo
Author-email: Jker_momo <16329024+jkermomo@user.noreply.gitee.com>
Requires-Dist: mcp[cli]>=1.21.1
Requires-Python: >=3.13.3
